PyRQP/__init__.py
PyRQP/rqp.py
PyRQP/utils.py
pyrqp-0.0.2.dist-info/LICENSE
pyrqp-0.0.2.dist-info/METADATA
pyrqp-0.0.2.dist-info/WHEEL
pyrqp-0.0.2.dist-info/top_level.txt
pyrqp-0.0.2.dist-info/RECORD
