Metadata-Version: 2.1
Name: pyrqp
Version: 0.0.2
Summary: An open source version of the Environment Agency's River Quality Planning software written in Python. It aims to be transparent, extendable and easy to automate.
Author-email: Pau Juan-Garcia <Pau.JuanGarcia@atkinsrealis.com>
Project-URL: Homepage, https://github.com/PauJuan/PyRQP
Project-URL: Bug Tracker, https://github.com/PauJuan/PyRQP/issues
Classifier: Programming Language :: Python :: 3
Classifier: License :: OSI Approved :: GNU General Public License v3 or later (GPLv3+)
Classifier: Operating System :: OS Independent
Requires-Python: >=3.7
License-File: LICENSE
